pic/__init__.py
pic/tqdm.png
xplan/__init__.py
xplan/dict_.py
xplan/iterable.py
xplan/string.py
xplan/eda/DataFrameSummary.py
xplan/eda/__init__.py
xplan/torch/__init__.py
xplan/torch/torch_summary.py
xplan/utils/__init__.py
xplan/utils/datafake.py
xplan/utils/decorator.py
xplan/utils/hive.py
xplan/utils/os_utils.py
xplan/utils/pkl.py
xplan/utils/plot.py
xplan/utils/time_utils.py
xplan/utils/twv.py
xplan/utils/x.py
x_plan-0.0.1.dist-info/LICENSE
x_plan-0.0.1.dist-info/METADATA
x_plan-0.0.1.dist-info/WHEEL
x_plan-0.0.1.dist-info/top_level.txt
x_plan-0.0.1.dist-info/RECORD
